CHANGELOG.txt
LICENSE
MANIFEST.in
README.md
setup.py
.vscode/settings.json
docs/conf.py
docs/_build/html/_sources/index.rst.txt
docs/_build/html/_sources/modules.rst.txt
docs/_build/html/_sources/setup.rst.txt
docs/_build/html/_sources/usgslidar.rst.txt
usgslidar/__init__.py
usgslidar/get_data.json
usgslidar/get_data.py
usgslidar/logs.py
usgslidar/visualize.py
usgslidar.egg-info/PKG-INFO
usgslidar.egg-info/SOURCES.txt
usgslidar.egg-info/dependency_links.txt
usgslidar.egg-info/requires.txt
usgslidar.egg-info/top_level.txt