Metadata-Version: 2.1
Name: usgslidar
Version: 0.0.23
Summary: A basic package to fetch USGs's LIDAR agriculture data
Home-page: UNKNOWN
Author: Azaria Gebremichael
Author-email: azariagebremichael10@gmail.com
License: MIT
Keywords: usgs,lidar
Platform: UNKNOWN
Classifier: Development Status :: 5 - Production/Stable
Classifier: Intended Audience :: Education
Classifier: Operating System :: Microsoft :: Windows :: Windows 10
Classifier: License :: OSI Approved :: MIT License
Classifier: Programming Language :: Python :: 3
